<annotation>
	<folder>Images</folder>
	<filename>vlcsnap-2021-01-05-22h10m26s238.png</filename>
	<path>C:\Users\Herberto\Desktop\UNI\4.Semester\EML\6_Projekt\EML_GIT\Images\vlcsnap-2021-01-05-22h10m26s238.png</path>
	<source>
		<database>Unknown</database>
	</source>
	<size>
		<width>640</width>
		<height>480</height>
		<depth>3</depth>
	</size>
	<segmented>0</segmented>
	<object>
		<name>cyclist</name>
		<pose>Unspecified</pose>
		<truncated>0</truncated>
		<difficult>0</difficult>
		<bndbox>
			<xmin>190</xmin>
			<ymin>160</ymin>
			<xmax>218</xmax>
			<ymax>215</ymax>
		</bndbox>
	</object>
</annotation>
